main.py
source_paystack/__init__.py
source_paystack/manifest.yaml
source_paystack/run.py
source_paystack/source.py
airbyte_source_paystack-1.0.11.dist-info/METADATA
airbyte_source_paystack-1.0.11.dist-info/WHEEL
airbyte_source_paystack-1.0.11.dist-info/entry_points.txt
airbyte_source_paystack-1.0.11.dist-info/RECORD
